openkitx403_client/__init__.py
openkitx403_client-0.1.5.dist-info/METADATA
openkitx403_client-0.1.5.dist-info/WHEEL
openkitx403_client-0.1.5.dist-info/RECORD
