Metadata-Version: 2.4
Name: openkitx403-client
Version: 0.1.5
Summary: Python client SDK for OpenKitx403 wallet authentication
License: MIT
Author: OpenKitx403 Contributors
Author-email: team@openkitx403.dev
Requires-Python: >=3.8,<4.0
Classifier: License :: OSI Approved :: MIT License
Classifier: Programming Language :: Python :: 3
Classifier: Programming Language :: Python :: 3.8
Classifier: Programming Language :: Python :: 3.9
Classifier: Programming Language :: Python :: 3.10
Classifier: Programming Language :: Python :: 3.11
Classifier: Programming Language :: Python :: 3.12
Classifier: Programming Language :: Python :: 3.13
Classifier: Programming Language :: Python :: 3.14
Requires-Dist: base58 (>=2.1.1,<3.0.0)
Requires-Dist: pynacl (>=1.5.0,<2.0.0)
Requires-Dist: requests (>=2.31.0,<3.0.0)
Requires-Dist: solders (>=0.18.1,<0.19.0)
Project-URL: Documentation, https://openkitx403.github.io/openkitx403-docs
Project-URL: Homepage, https://www.openkitx403.dev
Project-URL: Repository, https://github.com/openkitx403/openkitx403
